{
  "state": "IN_GAME",
  "secretCombination": {
    "colors": [
      "BLACK",
      "PINK",
      "YELLOW",
      "BLACK"
    ]
  },
  "proposedCombinations": [
    {
      "result": {
        "success": [
          "BLACK",
          "WHITE",
          "WHITE",
          null
        ]
      },
      "colors": [
        "BLACK",
        "BLACK",
        "WHITE",
        "PINK"
      ]
    },
    null,
    null,
    null,
    null
  ],
  "tries": 1,
  "careTaker": {
    "savedGames": [
      {
        "game": {
          "state": "IN_GAME",
          "secretCombination": {
            "colors": [
              "BLACK",
              "PINK",
              "YELLOW",
              "BLACK"
            ]
          },
          "proposedCombinations": [
            null,
            null,
            null,
            null,
            null
          ],
          "tries": 0,
          "careTaker": null
        }
      },
      {
        "game": {
          "state": "IN_GAME",
          "secretCombination": {
            "colors": [
              "BLACK",
              "PINK",
              "YELLOW",
              "BLACK"
            ]
          },
          "proposedCombinations": [
            {
              "result": {
                "success": [
                  "BLACK",
                  "WHITE",
                  "WHITE",
                  null
                ]
              },
              "colors": [
                "BLACK",
                "BLACK",
                "WHITE",
                "PINK"
              ]
            },
            null,
            null,
            null,
            null
          ],
          "tries": 1,
          "careTaker": null
        }
      }
    ],
    "current": 1
  }
}